coodeer/__init__.py
coodeer/cli/__init__.py
coodeer/cli/coodeer.py
coodeer/configuration/__init__.py
coodeer/configuration/coodeer.py
coodeer/controller/__init__.py
coodeer/controller/repository.py
coodeer/controller/s3_access.py
coodeer-0.4.14.dist-info/COPYING
coodeer-0.4.14.dist-info/METADATA
coodeer-0.4.14.dist-info/WHEEL
coodeer-0.4.14.dist-info/entry_points.txt
coodeer-0.4.14.dist-info/RECORD
